pstui/__init__.py
pstui/main.py
pstui-0.1.0.dist-info/LICENSE.md
pstui-0.1.0.dist-info/METADATA
pstui-0.1.0.dist-info/WHEEL
pstui-0.1.0.dist-info/entry_points.txt
pstui-0.1.0.dist-info/top_level.txt
pstui-0.1.0.dist-info/RECORD
