Metadata-Version: 2.1
Name: pstui
Version: 0.1.0
Summary: A terminal UI for managing processes
Author-email: tcsenpai <tcsenpai@discus.sh>
Project-URL: Homepage, https://github.com/tcsenpai/pstui
Project-URL: Repository, https://github.com/tcsenpai/pstui.git
Keywords: process,tui,system,monitor
Classifier: Programming Language :: Python :: 3
Classifier: License :: OSI Approved :: MIT License
Classifier: Operating System :: POSIX :: Linux
Classifier: Environment :: Console
Classifier: Intended Audience :: Developers
Classifier: Intended Audience :: System Administrators
Requires-Python: >=3.7
License-File: LICENSE.md
Requires-Dist: textual>=0.52.1
Requires-Dist: psutil>=5.9.0
